jocall3/__init__.py
jocall3/_base_client.py
jocall3/_client.py
jocall3/_compat.py
jocall3/_constants.py
jocall3/_exceptions.py
jocall3/_files.py
jocall3/_models.py
jocall3/_qs.py
jocall3/_resource.py
jocall3/_response.py
jocall3/_streaming.py
jocall3/_types.py
jocall3/_version.py
jocall3/py.typed
jocall3/_utils/__init__.py
jocall3/_utils/_compat.py
jocall3/_utils/_datetime_parse.py
jocall3/_utils/_logs.py
jocall3/_utils/_proxy.py
jocall3/_utils/_reflection.py
jocall3/_utils/_resources_proxy.py
jocall3/_utils/_streams.py
jocall3/_utils/_sync.py
jocall3/_utils/_transform.py
jocall3/_utils/_typing.py
jocall3/_utils/_utils.py
jocall3/lib/.keep
jocall3/resources/__init__.py
jocall3/resources/budgets.py
jocall3/resources/accounts/__init__.py
jocall3/resources/accounts/accounts.py
jocall3/resources/accounts/overdraft_settings.py
jocall3/resources/accounts/transactions.py
jocall3/resources/ai/__init__.py
jocall3/resources/ai/ads.py
jocall3/resources/ai/ai.py
jocall3/resources/ai/advisor/__init__.py
jocall3/resources/ai/advisor/advisor.py
jocall3/resources/ai/advisor/chat.py
jocall3/resources/ai/incubator/__init__.py
jocall3/resources/ai/incubator/incubator.py
jocall3/resources/ai/incubator/pitch.py
jocall3/resources/ai/oracle/__init__.py
jocall3/resources/ai/oracle/oracle.py
jocall3/resources/ai/oracle/simulate.py
jocall3/resources/ai/oracle/simulations.py
jocall3/resources/corporate/__init__.py
jocall3/resources/corporate/anomalies.py
jocall3/resources/corporate/cards.py
jocall3/resources/corporate/corporate.py
jocall3/resources/corporate/compliance/__init__.py
jocall3/resources/corporate/compliance/audits.py
jocall3/resources/corporate/compliance/compliance.py
jocall3/resources/corporate/risk/__init__.py
jocall3/resources/corporate/risk/risk.py
jocall3/resources/corporate/risk/fraud/__init__.py
jocall3/resources/corporate/risk/fraud/fraud.py
jocall3/resources/corporate/risk/fraud/rules.py
jocall3/resources/corporate/treasury/__init__.py
jocall3_python-0.0.3.dist-info/METADATA
jocall3_python-0.0.3.dist-info/WHEEL
jocall3_python-0.0.3.dist-info/licenses/LICENSE
jocall3_python-0.0.3.dist-info/RECORD
